pyagn/__init__.py
pyagn/constants.py
pyagn/sed.py
pyagn/xspec_routines.py
pyagn-0.2.0.dist-info/LICENSE
pyagn-0.2.0.dist-info/METADATA
pyagn-0.2.0.dist-info/WHEEL
pyagn-0.2.0.dist-info/top_level.txt
pyagn-0.2.0.dist-info/RECORD
