Metadata-Version: 2.1
Name: pyagn
Version: 0.2.0
Summary: PyAGN: A Python code about AGNs.
Home-page: https://github.com/arnauq/pyagn
Author: Arnau Quera-Bofarull
Author-email: arnau.quera-bofarull@durham.ac.uk
License: GNU GENERAL PUBLIC LICENSE
Requires-Dist: numpy
Requires-Dist: astropy
Requires-Dist: scipy
Requires-Dist: matplotlib
Requires-Dist: memoized-property
